cadence/__init__.py
cadence/__main__.py
cadence/api/__init__.py
cadence/api/routers/chat.py
cadence/api/routers/plugins.py
cadence/api/routers/system.py
cadence/api/routes.py
cadence/api/schemas.py
cadence/api/services.py
cadence/cli.py
cadence/config/__init__.py
cadence/config/settings.py
cadence/core/__init__.py
cadence/core/orchestrator/__init__.py
cadence/core/orchestrator/coordinator/__init__.py
cadence/core/orchestrator/coordinator/constants.py
cadence/core/orchestrator/coordinator/core.py
cadence/core/orchestrator/coordinator/enums.py
cadence/core/orchestrator/coordinator/graph_builder.py
cadence/core/orchestrator/coordinator/handlers.py
cadence/core/orchestrator/coordinator/model_factory.py
cadence/core/orchestrator/coordinator/prompts.py
cadence/core/orchestrator/coordinator/routing.py
cadence/core/schema/__init__.py
cadence/core/schema/runtime_collector.py
cadence/core/services/__init__.py
cadence/core/services/conversation_service.py
cadence/core/services/orchestrator_service.py
cadence/core/services/service_container.py
cadence/domain/__init__.py
cadence/domain/dtos/__init__.py
cadence/domain/dtos/analytics_dtos.py
cadence/domain/dtos/chat_dtos.py
cadence/domain/dtos/thread_dtos.py
cadence/domain/models/__init__.py
cadence/domain/models/conversation.py
cadence/domain/models/organization.py
cadence/domain/models/thread.py
cadence/domain/models/user.py
cadence/infrastructure/__init__.py
cadence/infrastructure/database/__init__.py
cadence/infrastructure/database/connection.py
cadence/infrastructure/database/factory.py
cadence/infrastructure/database/repositories/__init__.py
cadence/infrastructure/database/repositories/cassandra/__init__.py
cadence/infrastructure/database/repositories/conversation_repository.py
cadence/infrastructure/database/repositories/mariadb/__init__.py
cadence/infrastructure/database/repositories/mongo/__init__.py
cadence/infrastructure/database/repositories/postgres/__init__.py
cadence_py-1.3.0.dist-info/LICENSE
cadence_py-1.3.0.dist-info/METADATA
cadence_py-1.3.0.dist-info/WHEEL
cadence_py-1.3.0.dist-info/entry_points.txt
cadence_py-1.3.0.dist-info/RECORD
