Metadata-Version: 2.3
Name: cadence-py
Version: 1.3.0
Summary: Cadence AI - Multi-agent AI orchestration system with plugin management
License: MIT
Keywords: ai,agents,cadence-ai,orchestration,coordination,langchain,langgraph,multi-agent,cli
Author: Jonas Kahn
Author-email: me@ifelse.one
Requires-Python: >=3.13,<3.14
Classifier: Intended Audience :: Developers
Classifier: License :: OSI Approved :: MIT License
Classifier: Programming Language :: Python :: 3
Classifier: Programming Language :: Python :: 3.13
Classifier: Topic :: Software Development :: Libraries :: Python Modules
Classifier: Topic :: Scientific/Engineering :: Artificial Intelligence
Classifier: Framework :: FastAPI
Classifier: Environment :: Console
Classifier: Intended Audience :: System Administrators
Provides-Extra: dev
Requires-Dist: alembic (>=1.16.4,<2.0.0)
Requires-Dist: asyncpg (>=0.30.0,<0.31.0)
Requires-Dist: black (>=25.1.0,<26.0.0) ; extra == "dev"
Requires-Dist: click (>=8.2.1,<9.0.0)
Requires-Dist: fastapi (>=0.116.1,<0.117.0)
Requires-Dist: greenlet (>=3.2.4,<4.0.0)
Requires-Dist: httpx (>=0.28.1,<0.29.0)
Requires-Dist: isort (>=6.0.1,<7.0.0) ; extra == "dev"
Requires-Dist: langchain (>=0.3.27,<0.4.0)
Requires-Dist: langchain-anthropic (>=0.3.18,<0.4.0)
Requires-Dist: langchain-community (>=0.3.27,<0.4.0)
Requires-Dist: langchain-core (>=0.3.74,<0.4.0)
Requires-Dist: langchain-google-community (>=2.0.7,<3.0.0)
Requires-Dist: langchain-google-genai (>=2.1.9,<2.2.0)
Requires-Dist: langchain-google-vertexai (>=2.0.28,<3.0.0)
Requires-Dist: langchain-groq (>=0.3.7,<0.4.0)
Requires-Dist: langchain-openai (>=0.3.30,<0.4.0)
Requires-Dist: langchain-perplexity (>=0.1.2,<0.2.0)
Requires-Dist: langchain-xai (>=0.2.5,<0.3.0)
Requires-Dist: langgraph-checkpoint-redis (>=0.1.0,<0.2.0)
Requires-Dist: langgraph[add] (>=0.6.5,<0.7.0)
Requires-Dist: mypy (>=1.17.1,<2.0.0) ; extra == "dev"
Requires-Dist: pre-commit (>=4.3.0,<5.0.0) ; extra == "dev"
Requires-Dist: psycopg2-binary (>=2.9.10)
Requires-Dist: pydantic (>=2.11.7,<3.0.0)
Requires-Dist: pydantic-settings (>=2.10.1,<3.0.0)
Requires-Dist: pytest (>=8.4.1,<9.0.0) ; extra == "dev"
Requires-Dist: pytest-asyncio (>=1.1.0,<2.0.0) ; extra == "dev"
Requires-Dist: pytest-cov (>=6.2.1,<7.0.0) ; extra == "dev"
Requires-Dist: pytest-mock (>=3.14.1,<4.0.0) ; extra == "dev"
Requires-Dist: python-dotenv (>=1.1.1,<2.0.0)
Requires-Dist: python-multipart (>=0.0.20,<0.0.21)
Requires-Dist: redis (>=6.4.0,<7.0.0)
Requires-Dist: rich (>=14.1.0,<15.0.0)
Requires-Dist: ruff (>=0.12.9,<0.13.0) ; extra == "dev"
Requires-Dist: sqlalchemy (>=2.0.43,<3.0.0)
Requires-Dist: streamlit (>=1.48.1,<2.0.0)
Requires-Dist: twine (>=6.2.0) ; extra == "dev"
Requires-Dist: uvicorn[standard] (>=0.35.0,<0.36.0)
Project-URL: Documentation, https://cadence.readthedocs.io/
Project-URL: Homepage, https://github.com/jonaskahn/cadence
Project-URL: Repository, https://github.com/jonaskahn/cadence.git
Project-URL: issues, https://github.com/jonaskahn/cadence/issues
